imagemcp/__init__.py
imagemcp/_compat.py
imagemcp/cli.py
imagemcp/config.py
imagemcp/defaults.py
imagemcp/files.py
imagemcp/gallery.py
imagemcp/generator.py
imagemcp/ids.py
imagemcp/models.py
imagemcp/planner.py
imagemcp/sessions.py
imagemcp/slot_index.py
imagemcp/storage.py
imagemcp/templates_catalog.py
imagemcp/campaign/__init__.py
imagemcp/campaign/orchestrator.py
imagemcp/campaign/planner.py
imagemcp/campaign/runner.py
imagemcp/campaign/schemas.py
imagemcp/campaign/setup.py
imagemcp/campaign/status.py
imagemcp/campaign/workspace.py
imagemcp/data/__init__.py
imagemcp/data/placements_catalog.v0_1.json
imgen_cli-0.1.39.dist-info/METADATA
imgen_cli-0.1.39.dist-info/WHEEL
imgen_cli-0.1.39.dist-info/entry_points.txt
imgen_cli-0.1.39.dist-info/top_level.txt
imgen_cli-0.1.39.dist-info/RECORD
