Metadata-Version: 2.4
Name: imgen-cli
Version: 0.1.39
Summary: Planner + CLI for managing durable image slots and variants
Requires-Python: >=3.11
Requires-Dist: fastmcp>=2.12.3
Requires-Dist: httpx[http2]>=0.27.0
Requires-Dist: pillow>=10.0.0
Requires-Dist: pydantic>=2.6.0
Requires-Dist: pyyaml>=6.0.0
Provides-Extra: dev
Requires-Dist: pytest>=8.3.0; extra == "dev"
